<list>
  <ProcessDefinition>
    <processDefinitionPK>
      <companyId>1</companyId>
      <processId>rm_cadastro_produto_estoque</processId>
    </processDefinitionPK>
    <processDescription>Cadastro de Produto</processDescription>
    <instruction></instruction>
    <active>true</active>
    <publicProcess>false</publicProcess>
    <volumeId>Default</volumeId>
    <categoryId>BackOffice.Estoque.Cadastro de Produto</categoryId>
    <managerEngineAllocationId></managerEngineAllocationId>
    <snapshotFrequency>0</snapshotFrequency>
    <baseDay>0</baseDay>
    <baseMonth>0</baseMonth>
    <periodId>Default</periodId>
    <uniqueCardVersion>false</uniqueCardVersion>
    <keyWord></keyWord>
    <complementsLevel>1</complementsLevel>
    <notifyRequisitionerComplements>true</notifyRequisitionerComplements>
    <notifyManagerComplements>false</notifyManagerComplements>
    <deadlineTime>0</deadlineTime>
    <warningDeadlineTime>0</warningDeadlineTime>
    <notifyAuthorityComplements>true</notifyAuthorityComplements>
  </ProcessDefinition>
  <ProcessDefinitionVersion>
    <processDefinitionVersionPK>
      <companyId>1</companyId>
      <processId>Cadastro de Produto</processId>
      <version>9</version>
    </processDefinitionVersionPK>
    <versionDescription></versionDescription>
    <formId>123</formId>
    <editionMode>true</editionMode>
    <updateAttachmentsVersion>false</updateAttachmentsVersion>
    <controlsAttachmentsSecurity>false</controlsAttachmentsSecurity>
    <active>true</active>
    <blockedVersion>false</blockedVersion>
    <counterSign>false</counterSign>
    <openInstances>0</openInstances>
    <bpmnVersion>2</bpmnVersion>
    <processStates/>
    <favorito>false</favorito>
    <inheritFormSecurity>false</inheritFormSecurity>
    <mobileReady>false</mobileReady>
  </ProcessDefinitionVersion>
  <list>
    <ProcessState>
      <processStatePK>
        <companyId>1</companyId>
        <processId>rm_cadastro_produto_estoque</processId>
        <version>1</version>
        <sequence>4</sequence>
      </processStatePK>
      <stateName>Início</stateName>
      <stateDescription>Início</stateDescription>
      <instruction></instruction>
      <deadlineTime>0</deadlineTime>
      <joint>false</joint>
      <agreementPercentage>0</agreementPercentage>
      <engineAllocationId></engineAllocationId>
      <engineAllocationConfiguration></engineAllocationConfiguration>
      <selectColleague>1</selectColleague>
      <initialState>true</initialState>
      <notifyAuthorityDelay>true</notifyAuthorityDelay>
      <notifyRequisitionerDelay>false</notifyRequisitionerDelay>
      <allowanceAuthorityTime>3600</allowanceAuthorityTime>
      <frequenceAuthorityTime>3600</frequenceAuthorityTime>
      <allowanceRequisitionerTime>0</allowanceRequisitionerTime>
      <frequenceRequisitionerTime>0</frequenceRequisitionerTime>
      <transferAttachments>false</transferAttachments>
      <subProcessId></subProcessId>
      <formFolder>0</formFolder>
      <notifyAuthorityFollowUp>false</notifyAuthorityFollowUp>
      <notifyRequisitionerFollowUp>false</notifyRequisitionerFollowUp>
      <automatic>false</automatic>
      <positionX>150</positionX>
      <positionY>82</positionY>
      <forecastedEffortType>0</forecastedEffortType>
      <forecastedEffort>0</forecastedEffort>
      <notifyManagerFollowUp>false</notifyManagerFollowUp>
      <notifyManagerDelay>false</notifyManagerDelay>
      <allowanceManagerTime>0</allowanceManagerTime>
      <frequenceManagerTime>0</frequenceManagerTime>
      <inhibitTransfer>false</inhibitTransfer>
      <periodId></periodId>
      <stateType>0</stateType>
      <bpmnType>10</bpmnType>
      <signalId>0</signalId>
      <counterSign>false</counterSign>
      <openInstances>0</openInstances>
      <noticeExpirationAuthorityTime>0</noticeExpirationAuthorityTime>
      <noticeExpirationRequisitionerTime>0</noticeExpirationRequisitionerTime>
      <noticeExpirationManagerTime>0</noticeExpirationManagerTime>
      <destinationStates/>
      <digitalSignature>false</digitalSignature>
    </ProcessState>
    <ProcessState>
      <processStatePK>
        <companyId>1</companyId>
        <processId>rm_cadastro_produto_estoque</processId>
        <version>1</version>
        <sequence>5</sequence>
      </processStatePK>
      <stateName>Gestor</stateName>
      <stateDescription>Gestor</stateDescription>
      <instruction></instruction>
      <deadlineTime>0</deadlineTime>
      <deadlineFieldName></deadlineFieldName>
      <joint>false</joint>
      <agreementPercentage>0</agreementPercentage>
      <engineAllocationId>aprovadores</engineAllocationId>
      <engineAllocationConfiguration></engineAllocationConfiguration>
      <selectColleague>1</selectColleague>
      <initialState>false</initialState>
      <notifyAuthorityDelay>true</notifyAuthorityDelay>
      <notifyRequisitionerDelay>false</notifyRequisitionerDelay>
      <allowanceAuthorityTime>3600</allowanceAuthorityTime>
      <frequenceAuthorityTime>3600</frequenceAuthorityTime>
      <allowanceRequisitionerTime>0</allowanceRequisitionerTime>
      <frequenceRequisitionerTime>0</frequenceRequisitionerTime>
      <transferAttachments>false</transferAttachments>
      <subProcessId></subProcessId>
      <formFolder>0</formFolder>
      <notifyAuthorityFollowUp>true</notifyAuthorityFollowUp>
      <notifyRequisitionerFollowUp>false</notifyRequisitionerFollowUp>
      <automatic>false</automatic>
      <positionX>260</positionX>
      <positionY>208</positionY>
      <forecastedEffortType>0</forecastedEffortType>
      <forecastedEffort>0</forecastedEffort>
      <notifyManagerFollowUp>false</notifyManagerFollowUp>
      <notifyManagerDelay>false</notifyManagerDelay>
      <allowanceManagerTime>0</allowanceManagerTime>
      <frequenceManagerTime>0</frequenceManagerTime>
      <inhibitTransfer>false</inhibitTransfer>
      <periodId></periodId>
      <stateType>0</stateType>
      <bpmnType>80</bpmnType>
      <signalId>0</signalId>
      <counterSign>false</counterSign>
      <openInstances>0</openInstances>
      <noticeExpirationAuthorityTime>0</noticeExpirationAuthorityTime>
      <noticeExpirationRequisitionerTime>0</noticeExpirationRequisitionerTime>
      <noticeExpirationManagerTime>0</noticeExpirationManagerTime>
      <destinationStates/>
      <digitalSignature>false</digitalSignature>
      <executionType>0</executionType>
    </ProcessState>
    <ProcessState>
      <processStatePK>
        <companyId>1</companyId>
        <processId>rm_cadastro_produto_estoque</processId>
        <version>1</version>
        <sequence>20</sequence>
      </processStatePK>
      <stateName>Integração</stateName>
      <stateDescription>Integração</stateDescription>
      <instruction></instruction>
      <deadlineTime>0</deadlineTime>
      <deadlineFieldName></deadlineFieldName>
      <joint>false</joint>
      <agreementPercentage>0</agreementPercentage>
      <engineAllocationId></engineAllocationId>
      <selectColleague>1</selectColleague>
      <initialState>false</initialState>
      <notifyAuthorityDelay>false</notifyAuthorityDelay>
      <notifyRequisitionerDelay>false</notifyRequisitionerDelay>
      <allowanceAuthorityTime>0</allowanceAuthorityTime>
      <frequenceAuthorityTime>0</frequenceAuthorityTime>
      <allowanceRequisitionerTime>0</allowanceRequisitionerTime>
      <frequenceRequisitionerTime>0</frequenceRequisitionerTime>
      <transferAttachments>false</transferAttachments>
      <subProcessId></subProcessId>
      <formFolder>0</formFolder>
      <notifyAuthorityFollowUp>true</notifyAuthorityFollowUp>
      <notifyRequisitionerFollowUp>false</notifyRequisitionerFollowUp>
      <automatic>false</automatic>
      <positionX>260</positionX>
      <positionY>399</positionY>
      <forecastedEffortType>0</forecastedEffortType>
      <forecastedEffort>0</forecastedEffort>
      <notifyManagerFollowUp>false</notifyManagerFollowUp>
      <notifyManagerDelay>false</notifyManagerDelay>
      <allowanceManagerTime>0</allowanceManagerTime>
      <frequenceManagerTime>0</frequenceManagerTime>
      <inhibitTransfer>false</inhibitTransfer>
      <periodId></periodId>
      <stateType>0</stateType>
      <bpmnType>82</bpmnType>
      <signalId>0</signalId>
      <counterSign>false</counterSign>
      <openInstances>0</openInstances>
      <noticeExpirationAuthorityTime>0</noticeExpirationAuthorityTime>
      <noticeExpirationRequisitionerTime>0</noticeExpirationRequisitionerTime>
      <noticeExpirationManagerTime>0</noticeExpirationManagerTime>
      <destinationStates/>
      <digitalSignature>false</digitalSignature>
      <executionType>2</executionType>
    </ProcessState>
    <ProcessState>
      <processStatePK>
        <companyId>1</companyId>
        <processId>rm_cadastro_produto_estoque</processId>
        <version>1</version>
        <sequence>13</sequence>
      </processStatePK>
      <stateName>Fim</stateName>
      <stateDescription>Fim</stateDescription>
      <instruction>Atividade final do processo</instruction>
      <deadlineTime>0</deadlineTime>
      <joint>false</joint>
      <agreementPercentage>0</agreementPercentage>
      <engineAllocationId></engineAllocationId>
      <engineAllocationConfiguration></engineAllocationConfiguration>
      <selectColleague>0</selectColleague>
      <initialState>false</initialState>
      <notifyAuthorityDelay>true</notifyAuthorityDelay>
      <notifyRequisitionerDelay>false</notifyRequisitionerDelay>
      <allowanceAuthorityTime>0</allowanceAuthorityTime>
      <frequenceAuthorityTime>1</frequenceAuthorityTime>
      <allowanceRequisitionerTime>0</allowanceRequisitionerTime>
      <frequenceRequisitionerTime>0</frequenceRequisitionerTime>
      <transferAttachments>false</transferAttachments>
      <subProcessId></subProcessId>
      <formFolder>0</formFolder>
      <notifyAuthorityFollowUp>false</notifyAuthorityFollowUp>
      <notifyRequisitionerFollowUp>false</notifyRequisitionerFollowUp>
      <automatic>false</automatic>
      <positionX>513</positionX>
      <positionY>218</positionY>
      <forecastedEffortType>0</forecastedEffortType>
      <forecastedEffort>0</forecastedEffort>
      <notifyManagerFollowUp>false</notifyManagerFollowUp>
      <notifyManagerDelay>false</notifyManagerDelay>
      <allowanceManagerTime>0</allowanceManagerTime>
      <frequenceManagerTime>0</frequenceManagerTime>
      <inhibitTransfer>false</inhibitTransfer>
      <periodId></periodId>
      <stateType>6</stateType>
      <bpmnType>60</bpmnType>
      <signalId>0</signalId>
      <counterSign>false</counterSign>
      <openInstances>0</openInstances>
      <destinationStates/>
      <digitalSignature>false</digitalSignature>
    </ProcessState>
    <ProcessState>
      <processStatePK>
        <companyId>1</companyId>
        <processId>rm_cadastro_produto_estoque</processId>
        <version>1</version>
        <sequence>24</sequence>
      </processStatePK>
      <stateName>Fim</stateName>
      <stateDescription>Fim</stateDescription>
      <instruction>Atividade final do processo</instruction>
      <deadlineTime>0</deadlineTime>
      <joint>false</joint>
      <agreementPercentage>0</agreementPercentage>
      <engineAllocationId></engineAllocationId>
      <engineAllocationConfiguration></engineAllocationConfiguration>
      <selectColleague>0</selectColleague>
      <initialState>false</initialState>
      <notifyAuthorityDelay>true</notifyAuthorityDelay>
      <notifyRequisitionerDelay>false</notifyRequisitionerDelay>
      <allowanceAuthorityTime>0</allowanceAuthorityTime>
      <frequenceAuthorityTime>1</frequenceAuthorityTime>
      <allowanceRequisitionerTime>0</allowanceRequisitionerTime>
      <frequenceRequisitionerTime>0</frequenceRequisitionerTime>
      <transferAttachments>false</transferAttachments>
      <subProcessId></subProcessId>
      <formFolder>0</formFolder>
      <notifyAuthorityFollowUp>false</notifyAuthorityFollowUp>
      <notifyRequisitionerFollowUp>false</notifyRequisitionerFollowUp>
      <automatic>false</automatic>
      <positionX>513</positionX>
      <positionY>409</positionY>
      <forecastedEffortType>0</forecastedEffortType>
      <forecastedEffort>0</forecastedEffort>
      <notifyManagerFollowUp>false</notifyManagerFollowUp>
      <notifyManagerDelay>false</notifyManagerDelay>
      <allowanceManagerTime>0</allowanceManagerTime>
      <frequenceManagerTime>0</frequenceManagerTime>
      <inhibitTransfer>false</inhibitTransfer>
      <periodId></periodId>
      <stateType>6</stateType>
      <bpmnType>60</bpmnType>
      <signalId>0</signalId>
      <counterSign>false</counterSign>
      <openInstances>0</openInstances>
      <destinationStates/>
      <digitalSignature>false</digitalSignature>
    </ProcessState>
  </list>
  <list/>
  <list>
    <ProcessLink>
      <processLinkPK>
        <companyId>1</companyId>
        <processId>rm_cadastro_produto_estoque</processId>
        <version>1</version>
        <linkSequence>14</linkSequence>
      </processLinkPK>
      <actionLabel></actionLabel>
      <returnPermited>false</returnPermited>
      <initialStateSequence>5</initialStateSequence>
      <finalStateSequence>13</finalStateSequence>
      <returnLabel></returnLabel>
      <name></name>
      <automaticLink>false</automaticLink>
      <defaultLink>false</defaultLink>
      <type>0</type>
    </ProcessLink>
    <ProcessLink>
      <processLinkPK>
        <companyId>1</companyId>
        <processId>rm_cadastro_produto_estoque</processId>
        <version>1</version>
        <linkSequence>23</linkSequence>
      </processLinkPK>
      <actionLabel></actionLabel>
      <returnPermited>false</returnPermited>
      <initialStateSequence>5</initialStateSequence>
      <finalStateSequence>20</finalStateSequence>
      <returnLabel></returnLabel>
      <name></name>
      <automaticLink>false</automaticLink>
      <defaultLink>false</defaultLink>
      <type>0</type>
    </ProcessLink>
    <ProcessLink>
      <processLinkPK>
        <companyId>1</companyId>
        <processId>rm_cadastro_produto_estoque</processId>
        <version>1</version>
        <linkSequence>25</linkSequence>
      </processLinkPK>
      <actionLabel></actionLabel>
      <returnPermited>false</returnPermited>
      <initialStateSequence>20</initialStateSequence>
      <finalStateSequence>24</finalStateSequence>
      <returnLabel></returnLabel>
      <name></name>
      <automaticLink>false</automaticLink>
      <defaultLink>false</defaultLink>
      <type>0</type>
    </ProcessLink>
    <ProcessLink>
      <processLinkPK>
        <companyId>1</companyId>
        <processId>rm_cadastro_produto_estoque</processId>
        <version>1</version>
        <linkSequence>27</linkSequence>
      </processLinkPK>
      <actionLabel></actionLabel>
      <returnPermited>false</returnPermited>
      <initialStateSequence>4</initialStateSequence>
      <finalStateSequence>5</finalStateSequence>
      <returnLabel></returnLabel>
      <name></name>
      <automaticLink>false</automaticLink>
      <defaultLink>false</defaultLink>
      <type>0</type>
    </ProcessLink>
  </list>
  <list/>
  <list>
    <WorkflowProcessEvent>
      <workflowProcessEventPK>
        <companyId>1</companyId>
        <eventId>DataClientFluig</eventId>
        <processId>rm_cadastro_produto_estoque</processId>
        <version>1</version>
      </workflowProcessEventPK>
      <eventDescription>/**&apos;&#xd;
* A API de autenticação da Totvs baseia no &quot;Basic access authentication&quot; do HTTP.&#xd;
 * Código Java para autenticação &#xd;
 * Programa responsável por integrar com os Webservices do RM &#xd;
 *  Exemplo dev valores para os parâmetros &#xd;
 *		@param string Usuario = &quot;mestre&quot;;&#xd;
 *		@param string Senha = &quot;totvs&quot;;&#xd;
*/&#xd;
&#xd;
function getWebService(Usuario, Senha){&#xd;
&#xd;
    var Nome_Servico = &quot;WSDATASERVER&quot;;&#xd;
    var Caminho_Servico = &quot;com.totvs.WsDataServer&quot;;&#xd;
    &#xd;
	var dataServerService = ServiceManager.getServiceInstance(Nome_Servico);&#xd;
	if(dataServerService == null){&#xd;
		throw &quot;Servico nao encontrado: &quot; + Nome_Servico;&#xd;
	}&#xd;
	&#xd;
	var serviceLocator = dataServerService.instantiate(Caminho_Servico);&#xd;
	if(serviceLocator == null){&#xd;
		throw &quot;Instancia do servico nao encontrada: &quot; + Nome_Servico + &quot; - &quot; + Caminho_Servico;&#xd;
	}&#xd;
&#xd;
	var service = serviceLocator.getRMIwsDataServer();	&#xd;
	if(service == null){&#xd;
		throw &quot;Instancia do dataserver do invalida: &quot; + Nome_Servico + &quot; - &quot; + Caminho_Servico;&#xd;
	}&#xd;
&#xd;
	var serviceHelper = dataServerService.getBean();&#xd;
	if(serviceHelper == null){&#xd;
		throw &quot;Instancia do service helper invalida: &quot; + Nome_Servico + &quot; - &quot; + Caminho_Servico;&#xd;
	}&#xd;
&#xd;
	var authService = serviceHelper.getBasicAuthenticatedClient(service, &quot;com.totvs.IwsDataServer&quot;, Usuario, Senha);	  &#xd;
	if(serviceHelper == null){&#xd;
		throw &quot;Instancia do auth service invalida: &quot; + Nome_Servico + &quot; - &quot; + Caminho_Servico;&#xd;
	}&#xd;
	&#xd;
	return authService;&#xd;
}&#xd;
&#xd;
&#xd;
function dcReadView(dataservername, context, usuario, senha, filtro)&#xd;
{	 &#xd;
      // carrega o webservice...&#xd;
	  var authService = getWebService(usuario, senha);&#xd;
	  &#xd;
      // lê os dados da visão respeitando o filtro passado&#xd;
	  var viewData = new String(authService.readView(dataservername, filtro, context));&#xd;
&#xd;
	  return viewData;&#xd;
 }&#xd;
&#xd;
&#xd;
function dcReadRecord(dataservername, context, usuario, senha, primaryKey)&#xd;
{	 &#xd;
      // carrega o webservice...&#xd;
	  var authService = getWebService(usuario, senha);&#xd;
&#xd;
      // lê os dados do registro respeitando a pk passada&#xd;
	  try&#xd;
	  {&#xd;
		var recordData = new String(authService.readRecord(dataservername, primaryKey, context));&#xd;
	  }&#xd;
	  catch (e) &#xd;
	  {&#xd;
		  var recordData = new String(authService.getSchema(dataservername, context));&#xd;
	  }&#xd;
	  &#xd;
	  return recordData;&#xd;
 }&#xd;
  &#xd;
 &#xd;
function dcSaveRecord(dataservername, context, usuario, senha, xml)&#xd;
{	 &#xd;
      // carrega o webservice...&#xd;
	  var authService = getWebService(usuario, senha);&#xd;
&#xd;
      // salva o registro de acordo com o xml passado&#xd;
	  var pk = new String(authService.readRecord(dataservername, xml, context));&#xd;
	  	  &#xd;
	  return pk;&#xd;
 }&#xd;
 &#xd;
 &#xd;
//Transforma o conceito de constraints do Fluig para o Filtro do TBC.&#xd;
function parseConstraints(constraints, filterRequired)&#xd;
{&#xd;
	// inicializa o resultado...&#xd;
	var result = [];&#xd;
	result.context = &quot;&quot;;&#xd;
	&#xd;
	// inicializa o filtro...&#xd;
	var filter = &quot;&quot;;&#xd;
	&#xd;
	// varre as contraints...&#xd;
    for	(con in constraints) {&#xd;
    	var fieldName = con.getFieldName().toUpperCase();&#xd;
    	if (fieldName == &quot;RMSCONTEXT&quot;)&#xd;
    	{&#xd;
    		result.context = con.getInitialValue();&#xd;
    		continue;&#xd;
    	}&#xd;
    	&#xd;
    	filter += &quot;(&quot;;&#xd;
    	&#xd;
    	if (fieldName == &quot;RMSFILTER&quot;)&#xd;
		{&#xd;
    		filter += con.getInitialValue();&#xd;
		}&#xd;
    	else&#xd;
		{&#xd;
    		if (con.getInitialValue() == con.getFinalValue() || isEmpty(con.getFinalValue()))&#xd;
			{&#xd;
				filter += con.getFieldName();&#xd;
				var isLike = false;&#xd;
				switch(con.getConstraintType())&#xd;
				{&#xd;
					case ConstraintType.MUST:&#xd;
						filter += &quot; = &quot;;&#xd;
					break;&#xd;
					case ConstraintType.MUST_NOT:&#xd;
						filter += &quot; = &quot;;&#xd;
					break;&#xd;
					case ConstraintType.SHOULD:&#xd;
						filter += &quot; LIKE &quot;;&#xd;
						isLike = true;&#xd;
					break;&#xd;
					case ConstraintType.SHOULD_NOT:&#xd;
						filter += &quot; NOT LIKE &quot;;&#xd;
						isLike = true;&#xd;
					break;&#xd;
				}&#xd;
				filter += getFormattedValue(con.getInitialValue(), isLike);&#xd;
			}&#xd;
    		else&#xd;
			{&#xd;
    			filter += con.getFieldName();&#xd;
    			filter += &quot; BETWEEN &quot;;&#xd;
    			filter += getFormattedValue(con.getInitialValue(), false);&#xd;
    			filter += &quot; AND &quot;;&#xd;
    			filter += getFormattedValue(con.getFinalValue(), false);&#xd;
			}&#xd;
		}&#xd;
    	&#xd;
		filter += &quot;) AND &quot;;&#xd;
	}&#xd;
    &#xd;
    if (filter.length == 0)&#xd;
    {&#xd;
    	if(filterRequired){&#xd;
    	  filter = &quot;1=1&quot;;&#xd;
    	}&#xd;
    	else{&#xd;
      	  filter = &quot;1=1&quot;;&#xd;
    	}&#xd;
    }&#xd;
    else&#xd;
    	filter = filter.substring(0, filter.length-5);&#xd;
    &#xd;
    // guarda o filtro...&#xd;
    result.filter = filter;&#xd;
    &#xd;
    // retorna o resultado...&#xd;
    return result;&#xd;
}&#xd;
&#xd;
function isEmpty(str) {&#xd;
    return (!str || 0 === str.length);&#xd;
}&#xd;
&#xd;
function getFormattedValue(value, isLike){&#xd;
	if(isLike){&#xd;
	  return &quot;&apos;%&quot; + value + &quot;%&apos;&quot;;&#xd;
	}&#xd;
	else{&#xd;
	  return &quot;&apos;&quot; + value + &quot;&apos;&quot;;&#xd;
	}&#xd;
}&#xd;
&#xd;
&#xd;
&#xd;
function getXMLFromString(xmlString) {&#xd;
	var factory = javax.xml.parsers.DocumentBuilderFactory.newInstance();&#xd;
	var parser = factory.newDocumentBuilder();&#xd;
	var is = new org.xml.sax.InputSource();&#xd;
    is.setCharacterStream(new java.io.StringReader(xmlString));&#xd;
	return parser.parse(is);&#xd;
}&#xd;
&#xd;
 &#xd;
 function abrirPesquisa(DATASET_ID, dataFields, resultFields, type, title){	&#xd;
	window.open(&quot;/webdesk/zoom.jsp&quot; +&#xd;
	&quot;?datasetId=&quot; +&#xd;
	DATASET_ID +&#xd;
	&quot;&amp;dataFields=&quot; +&#xd;
	dataFields +&#xd;
	&quot;&amp;resultFields=&quot; +&#xd;
	resultFields +&#xd;
	&quot;&amp;type=&quot; +&#xd;
	type+&#xd;
	&quot;&amp;title=&quot; +&#xd;
	title 	&#xd;
	, &quot;zoom&quot;, &quot;status,scroolbars=no,width=600,height=350,top=0,left=0&quot;);&#xd;
}&#xd;
&#xd;
function checkIsPK(result, qtd){&#xd;
	var lines = result.split(&apos;\r&apos;);&#xd;
	&#xd;
	if(lines.length == 1){&#xd;
		var pk = result.split(&apos;;&apos;);&#xd;
		if(pk.length == qtd)&#xd;
			return;&#xd;
	}&#xd;
		throw result;&#xd;
	&#xd;
}&#xd;
&#xd;
 function ChekExist(result)&#xd;
 {&#xd;
	 var lines = result.split(&apos;\r&apos;);&#xd;
	if(lines.length &gt; 1)&#xd;
		return true&#xd;
	else&#xd;
		return false;&#xd;
 }&#xd;
 &#xd;
&#xd;
function replaceValue(text, columnName, newValue){&#xd;
&#xd;
	&#xd;
	if ((newValue != null) &amp;&amp; (newValue.trim() != &quot;&quot;))&#xd;
	{&#xd;
		var regex = new RegExp(&quot;&lt;&quot; + columnName + &quot;&gt;(.*?)&lt;\\/&quot; + columnName + &quot;&gt;&quot;, &quot;g&quot;);&#xd;
		var replaceText = &quot;&lt;&quot; + columnName + &quot;&gt;&quot; + newValue + &quot;&lt;/&quot; + columnName + &quot;&gt;&quot;;&#xd;
		&#xd;
		return text.replace(regex, replaceText);&#xd;
	}&#xd;
	else&#xd;
		return text;&#xd;
}&#xd;
&#xd;
&#xd;
function isEmpty(str) {&#xd;
    return (!str || 0 === str.length);&#xd;
}&#xd;
</eventDescription>
    </WorkflowProcessEvent>
    <WorkflowProcessEvent>
      <workflowProcessEventPK>
        <companyId>1</companyId>
        <eventId>servicetask20</eventId>
        <processId>rm_cadastro_produto_estoque</processId>
        <version>1</version>
      </workflowProcessEventPK>
      <eventDescription>// Programa responsável por integrar com os Webservices do RM  
// Para executar o programa, seguir os passos abaixo:  
//    1) Adicionar o arquivo abaixo ao seu projeto:  
//            http://tdn.totvs.com/download/attachments/211064343/DataClientfluig.js  
//     2) Inclua um serviço no Fluig com o nome WSDATASERVER apontando para    
//       http://localhost:8051/wsDataServer/MEX?singlewsdl (substituir localhost pelo IP e Porta do servidor RM)//.  

function servicetask20(attempt, message) {

	var NOME_DATASERVER = &quot;EstPrdDataBR&quot;;  
	  
    /* Prepararação das variaveis */  
      //usuário e senha do aplicativo RM. O mesmo utilizado para logar no sistema e que tenha permissão de   
      //acesso ao cadastro que deseja utilizar  
      var usuario = &quot;mestre&quot;;  
      var senha = &quot;totvs&quot;;  
      //importante passar no contexto o mesmo código de usuário usado para logar no webservice  
      var context = &quot;CODSISTEMA=G;CODCOLIGADA=1;CODUSUARIO=mestre&quot;  
    /* Fim Prepararação das variaveis */  
        
  
    try{  
          
        if (isEmpty(hAPI.getCardValue(&quot;CODCOLIGADA&quot;)) || isEmpty(hAPI.getCardValue(&quot;IDPRD&quot;)))     
        return      
        var primaryKey = hAPI.getCardValue(&quot;CODCOLIGADA&quot;) + &quot;;&quot; + hAPI.getCardValue(&quot;IDPRD&quot;);  
  
        // carrega o webservice...  
        var authService = getWebService(usuario, senha);  
        // define o contexto...  
        var context = &quot;CODSISTEMA=G;CODCOLIGADA=1;CODUSUARIO=mestre&quot;  
        // faz a leitura...  
        var text = new String(authService.readRecord(NOME_DATASERVER, primaryKey, context));  
  
        if (!ChekExist(text))  
            text = GetXml();  
  
      
	    // atualiza o valor...    
        text = replaceValue(text, &quot;CODIGOPRD&quot; , hAPI.getCardValue(&quot;CODIGOPRD&quot;));   
        text = replaceValue(text, &quot;CODCOLIGADA&quot; , hAPI.getCardValue(&quot;CODCOLIGADA&quot;));   
        text = replaceValue(text, &quot;IDPRD&quot; , hAPI.getCardValue(&quot;IDPRD&quot;));   
        text = replaceValue(text, &quot;NOMEFANTASIA&quot; , hAPI.getCardValue(&quot;NOMEFANTASIA&quot;));   
        text = replaceValue(text, &quot;DESCRICAO&quot; , hAPI.getCardValue(&quot;DESCRICAO&quot;));   


        var result = new String(authService.saveRecord(NOME_DATASERVER, text, context));   
          
    // se retornou a chave, salvou ok...  
        checkIsPK(result, 2);  
    }  
    catch (e)   
    {  
        if (e == null)  e = &quot;Erro desconhecido!&quot;;  
        var mensagemErro = &quot;Ocorreu um erro ao salvar dados no RM: &quot; + e;  
        throw mensagemErro;  
    }     
}  
  
          
function GetXml()  
{  
    return &quot;&lt;EstPrdBR &gt;&quot; +   
&quot;  &lt;TPRODUTO&gt;&quot; +   
&quot;    &lt;CODCOLPRD&gt;1&lt;/CODCOLPRD&gt;&quot; +   
&quot;    &lt;CODCOLIGADA&gt;1&lt;/CODCOLIGADA&gt;&quot; +   
&quot;    &lt;IDPRD&gt;1&lt;/IDPRD&gt;&quot; +   
&quot;    &lt;CODIGOPRD&gt;01&lt;/CODIGOPRD&gt;&quot; +   
&quot;    &lt;NOMEFANTASIA&gt;CD&apos;s&lt;/NOMEFANTASIA&gt;&quot; +   
&quot;    &lt;CODIGOREDUZIDO&gt;0001&lt;/CODIGOREDUZIDO&gt;&quot; +   
&quot;    &lt;CODFAB&gt;6.02&lt;/CODFAB&gt;&quot; +   
&quot;    &lt;NUMNOFABRIC&gt;1&lt;/NUMNOFABRIC&gt;&quot; +   
&quot;    &lt;ULTIMONIVEL&gt;0&lt;/ULTIMONIVEL&gt;&quot; +   
&quot;    &lt;TIPO&gt;P&lt;/TIPO&gt;&quot; +   
&quot;    &lt;DESCRICAO&gt;CD&apos;s&lt;/DESCRICAO&gt;&quot; +   
&quot;    &lt;PRECO1&gt;0.0000&lt;/PRECO1&gt;&quot; +   
&quot;    &lt;PRECO2&gt;0.0000&lt;/PRECO2&gt;&quot; +   
&quot;    &lt;PRECO3&gt;0.0000&lt;/PRECO3&gt;&quot; +   
&quot;    &lt;PRECO4&gt;0.0000&lt;/PRECO4&gt;&quot; +   
&quot;    &lt;PRECO5&gt;0.0000&lt;/PRECO5&gt;&quot; +   
&quot;    &lt;DATABASEPRECO1&gt;1996-07-05T00:00:00&lt;/DATABASEPRECO1&gt;&quot; +   
&quot;    &lt;DATABASEPRECO2&gt;1996-07-05T00:00:00&lt;/DATABASEPRECO2&gt;&quot; +   
&quot;    &lt;DATABASEPRECO3&gt;1996-07-05T00:00:00&lt;/DATABASEPRECO3&gt;&quot; +   
&quot;    &lt;DATABASEPRECO4&gt;1996-07-05T00:00:00&lt;/DATABASEPRECO4&gt;&quot; +   
&quot;    &lt;DATABASEPRECO5&gt;1996-07-05T00:00:00&lt;/DATABASEPRECO5&gt;&quot; +   
&quot;    &lt;CODMOEPRECO1&gt;R$&lt;/CODMOEPRECO1&gt;&quot; +   
&quot;    &lt;CODMOEPRECO2&gt;R$&lt;/CODMOEPRECO2&gt;&quot; +   
&quot;    &lt;CODMOEPRECO3&gt;R$&lt;/CODMOEPRECO3&gt;&quot; +   
&quot;    &lt;CODMOEPRECO4&gt;UFIR&lt;/CODMOEPRECO4&gt;&quot; +   
&quot;    &lt;CODMOEPRECO5&gt;R$&lt;/CODMOEPRECO5&gt;&quot; +   
&quot;    &lt;REFERENCIACP&gt;1&lt;/REFERENCIACP&gt;&quot; +   
&quot;    &lt;PESOLIQUIDO&gt;0.0000&lt;/PESOLIQUIDO&gt;&quot; +   
&quot;    &lt;PESOBRUTO&gt;0.0000&lt;/PESOBRUTO&gt;&quot; +   
&quot;    &lt;COMPRIMENTO&gt;0.0000&lt;/COMPRIMENTO&gt;&quot; +   
&quot;    &lt;ESPESSURA&gt;0.0000&lt;/ESPESSURA&gt;&quot; +   
&quot;    &lt;LARGURA&gt;0.0000&lt;/LARGURA&gt;&quot; +   
&quot;    &lt;CODUNDCONTROLE&gt;UN&lt;/CODUNDCONTROLE&gt;&quot; +   
&quot;    &lt;ESTOQUEMINIMO1&gt;0.0000&lt;/ESTOQUEMINIMO1&gt;&quot; +   
&quot;    &lt;ESTOQUEMAXIMO1&gt;0.0000&lt;/ESTOQUEMAXIMO1&gt;&quot; +   
&quot;    &lt;ESTOQUEMINIMO2&gt;0.0000&lt;/ESTOQUEMINIMO2&gt;&quot; +   
&quot;    &lt;ESTOQUEMAXIMO2&gt;0.0000&lt;/ESTOQUEMAXIMO2&gt;&quot; +   
&quot;    &lt;ESTOQUEMINIMO3&gt;0.0000&lt;/ESTOQUEMINIMO3&gt;&quot; +   
&quot;    &lt;ESTOQUEMAXIMO3&gt;0.0000&lt;/ESTOQUEMAXIMO3&gt;&quot; +   
&quot;    &lt;PONTODEPEDIDO1&gt;0.0000&lt;/PONTODEPEDIDO1&gt;&quot; +   
&quot;    &lt;PONTODEPEDIDO2&gt;0.0000&lt;/PONTODEPEDIDO2&gt;&quot; +   
&quot;    &lt;PONTODEPEDIDO3&gt;0.0000&lt;/PONTODEPEDIDO3&gt;&quot; +   
&quot;    &lt;DTCADASTRAMENTO&gt;1996-03-18T00:00:00&lt;/DTCADASTRAMENTO&gt;&quot; +   
&quot;    &lt;PERCENTCOMISSAO&gt;0.0000&lt;/PERCENTCOMISSAO&gt;&quot; +   
&quot;    &lt;DESCONTOCOMPRA&gt;0.0000&lt;/DESCONTOCOMPRA&gt;&quot; +   
&quot;    &lt;DESCONTOVENDA&gt;0.0000&lt;/DESCONTOVENDA&gt;&quot; +   
&quot;    &lt;CUSTOUNITARIO&gt;0.0000&lt;/CUSTOUNITARIO&gt;&quot; +   
&quot;    &lt;CODTIP&gt;01&lt;/CODTIP&gt;&quot; +   
&quot;    &lt;CODTB2FAT&gt;002&lt;/CODTB2FAT&gt;&quot; +   
&quot;    &lt;CODTB3FAT&gt;001&lt;/CODTB3FAT&gt;&quot; +   
&quot;    &lt;MARGEMBRUTALUCRO&gt;0.0000&lt;/MARGEMBRUTALUCRO&gt;&quot; +   
&quot;    &lt;PERCENTCOMISSAO2&gt;0.0000&lt;/PERCENTCOMISSAO2&gt;&quot; +   
&quot;    &lt;QTDEVOLUME&gt;1&lt;/QTDEVOLUME&gt;&quot; +   
&quot;    &lt;CODUNDCOMPRA&gt;UN&lt;/CODUNDCOMPRA&gt;&quot; +   
&quot;    &lt;CODUNDVENDA&gt;UN&lt;/CODUNDVENDA&gt;&quot; +   
&quot;    &lt;EPERIODICO&gt;0&lt;/EPERIODICO&gt;&quot; +   
&quot;    &lt;CAMPOLIVRE&gt;112&lt;/CAMPOLIVRE&gt;&quot; +   
&quot;    &lt;CAMPOLIVRE2&gt;l;&lt;/CAMPOLIVRE2&gt;&quot; +   
&quot;    &lt;CAMPOLIVRE3&gt;l;&lt;/CAMPOLIVRE3&gt;&quot; +   
&quot;    &lt;CUSTOMEDIO&gt;0.0000&lt;/CUSTOMEDIO&gt;&quot; +   
&quot;    &lt;CUSTOREPOSICAO&gt;0.0000&lt;/CUSTOREPOSICAO&gt;&quot; +   
&quot;    &lt;CUSTOREPOSICAOB&gt;0.0000&lt;/CUSTOREPOSICAOB&gt;&quot; +   
&quot;    &lt;USANUMDECPRECO&gt;0&lt;/USANUMDECPRECO&gt;&quot; +   
&quot;    &lt;CLASSEFISCALECF&gt;0&lt;/CLASSEFISCALECF&gt;&quot; +   
&quot;    &lt;INATIVO&gt;0&lt;/INATIVO&gt;&quot; +   
&quot;    &lt;PESAVEL&gt;0&lt;/PESAVEL&gt;&quot; +   
&quot;    &lt;DATAULTALTERACAO&gt;2005-04-19T00:00:00&lt;/DATAULTALTERACAO&gt;&quot; +   
&quot;    &lt;CODUSUARIO&gt;Carlos Alberto&lt;/CODUSUARIO&gt;&quot; +   
&quot;    &lt;MARGEMLUCROFISC&gt;0.0000&lt;/MARGEMLUCROFISC&gt;&quot; +   
&quot;    &lt;PRODUTOBASE&gt;0&lt;/PRODUTOBASE&gt;&quot; +   
&quot;    &lt;SERVICOPRODUTORMOFFICINA&gt;1&lt;/SERVICOPRODUTORMOFFICINA&gt;&quot; +   
&quot;    &lt;TRIBUTACAOECF&gt;T07&lt;/TRIBUTACAOECF&gt;&quot; +   
&quot;    &lt;PRODVISIVELCLICBUSINESS&gt;1&lt;/PRODVISIVELCLICBUSINESS&gt;&quot; +   
&quot;  &lt;/TPRODUTO&gt;&quot; +   
&quot;  &lt;TPrdFil&gt;&quot; +   
&quot;    &lt;CODCOLIGADA&gt;1&lt;/CODCOLIGADA&gt;&quot; +   
&quot;    &lt;IDPRD&gt;1&lt;/IDPRD&gt;&quot; +   
&quot;    &lt;CODFILIAL&gt;1&lt;/CODFILIAL&gt;&quot; +   
&quot;    &lt;ESTOCAVEL&gt;1&lt;/ESTOCAVEL&gt;&quot; +   
&quot;    &lt;CONSIGNADO&gt;0&lt;/CONSIGNADO&gt;&quot; +   
&quot;  &lt;/TPrdFil&gt;&quot; +   
&quot;  &lt;TPrdFil&gt;&quot; +   
&quot;    &lt;CODCOLIGADA&gt;1&lt;/CODCOLIGADA&gt;&quot; +   
&quot;    &lt;IDPRD&gt;1&lt;/IDPRD&gt;&quot; +   
&quot;    &lt;CODFILIAL&gt;2&lt;/CODFILIAL&gt;&quot; +   
&quot;    &lt;ESTOCAVEL&gt;1&lt;/ESTOCAVEL&gt;&quot; +   
&quot;    &lt;CONSIGNADO&gt;0&lt;/CONSIGNADO&gt;&quot; +   
&quot;  &lt;/TPrdFil&gt;&quot; +   
&quot;  &lt;TPrdFil&gt;&quot; +   
&quot;    &lt;CODCOLIGADA&gt;1&lt;/CODCOLIGADA&gt;&quot; +   
&quot;    &lt;IDPRD&gt;1&lt;/IDPRD&gt;&quot; +   
&quot;    &lt;CODFILIAL&gt;3&lt;/CODFILIAL&gt;&quot; +   
&quot;    &lt;ESTOCAVEL&gt;1&lt;/ESTOCAVEL&gt;&quot; +   
&quot;    &lt;CONSIGNADO&gt;0&lt;/CONSIGNADO&gt;&quot; +   
&quot;  &lt;/TPrdFil&gt;&quot; +   
&quot;  &lt;TPrdFil&gt;&quot; +   
&quot;    &lt;CODCOLIGADA&gt;1&lt;/CODCOLIGADA&gt;&quot; +   
&quot;    &lt;IDPRD&gt;1&lt;/IDPRD&gt;&quot; +   
&quot;    &lt;CODFILIAL&gt;4&lt;/CODFILIAL&gt;&quot; +   
&quot;    &lt;ESTOCAVEL&gt;1&lt;/ESTOCAVEL&gt;&quot; +   
&quot;    &lt;CONSIGNADO&gt;0&lt;/CONSIGNADO&gt;&quot; +   
&quot;  &lt;/TPrdFil&gt;&quot; +   
&quot;  &lt;TPrdFil&gt;&quot; +   
&quot;    &lt;CODCOLIGADA&gt;1&lt;/CODCOLIGADA&gt;&quot; +   
&quot;    &lt;IDPRD&gt;1&lt;/IDPRD&gt;&quot; +   
&quot;    &lt;CODFILIAL&gt;5&lt;/CODFILIAL&gt;&quot; +   
&quot;    &lt;ESTOCAVEL&gt;1&lt;/ESTOCAVEL&gt;&quot; +   
&quot;    &lt;CONSIGNADO&gt;0&lt;/CONSIGNADO&gt;&quot; +   
&quot;  &lt;/TPrdFil&gt;&quot; +   
&quot;  &lt;TPrdFil&gt;&quot; +   
&quot;    &lt;CODCOLIGADA&gt;1&lt;/CODCOLIGADA&gt;&quot; +   
&quot;    &lt;IDPRD&gt;1&lt;/IDPRD&gt;&quot; +   
&quot;    &lt;CODFILIAL&gt;6&lt;/CODFILIAL&gt;&quot; +   
&quot;    &lt;ESTOCAVEL&gt;1&lt;/ESTOCAVEL&gt;&quot; +   
&quot;    &lt;CONSIGNADO&gt;0&lt;/CONSIGNADO&gt;&quot; +   
&quot;  &lt;/TPrdFil&gt;&quot; +   
&quot;  &lt;TPrdFil&gt;&quot; +   
&quot;    &lt;CODCOLIGADA&gt;1&lt;/CODCOLIGADA&gt;&quot; +   
&quot;    &lt;IDPRD&gt;1&lt;/IDPRD&gt;&quot; +   
&quot;    &lt;CODFILIAL&gt;7&lt;/CODFILIAL&gt;&quot; +   
&quot;    &lt;ESTOCAVEL&gt;1&lt;/ESTOCAVEL&gt;&quot; +   
&quot;    &lt;CONSIGNADO&gt;0&lt;/CONSIGNADO&gt;&quot; +   
&quot;  &lt;/TPrdFil&gt;&quot; +   
&quot;  &lt;TPrdFil&gt;&quot; +   
&quot;    &lt;CODCOLIGADA&gt;1&lt;/CODCOLIGADA&gt;&quot; +   
&quot;    &lt;IDPRD&gt;1&lt;/IDPRD&gt;&quot; +   
&quot;    &lt;CODFILIAL&gt;8&lt;/CODFILIAL&gt;&quot; +   
&quot;    &lt;ESTOCAVEL&gt;1&lt;/ESTOCAVEL&gt;&quot; +   
&quot;    &lt;CONSIGNADO&gt;0&lt;/CONSIGNADO&gt;&quot; +   
&quot;  &lt;/TPrdFil&gt;&quot; +   
&quot;  &lt;TPrdFil&gt;&quot; +   
&quot;    &lt;CODCOLIGADA&gt;1&lt;/CODCOLIGADA&gt;&quot; +   
&quot;    &lt;IDPRD&gt;1&lt;/IDPRD&gt;&quot; +   
&quot;    &lt;CODFILIAL&gt;9&lt;/CODFILIAL&gt;&quot; +   
&quot;    &lt;ESTOCAVEL&gt;1&lt;/ESTOCAVEL&gt;&quot; +   
&quot;    &lt;CONSIGNADO&gt;0&lt;/CONSIGNADO&gt;&quot; +   
&quot;  &lt;/TPrdFil&gt;&quot; +   
&quot;  &lt;TPrdFil&gt;&quot; +   
&quot;    &lt;CODCOLIGADA&gt;1&lt;/CODCOLIGADA&gt;&quot; +   
&quot;    &lt;IDPRD&gt;1&lt;/IDPRD&gt;&quot; +   
&quot;    &lt;CODFILIAL&gt;10&lt;/CODFILIAL&gt;&quot; +   
&quot;    &lt;ESTOCAVEL&gt;1&lt;/ESTOCAVEL&gt;&quot; +   
&quot;    &lt;CONSIGNADO&gt;0&lt;/CONSIGNADO&gt;&quot; +   
&quot;  &lt;/TPrdFil&gt;&quot; +   
&quot;  &lt;TPrdFil&gt;&quot; +   
&quot;    &lt;CODCOLIGADA&gt;1&lt;/CODCOLIGADA&gt;&quot; +   
&quot;    &lt;IDPRD&gt;1&lt;/IDPRD&gt;&quot; +   
&quot;    &lt;CODFILIAL&gt;11&lt;/CODFILIAL&gt;&quot; +   
&quot;    &lt;ESTOCAVEL&gt;1&lt;/ESTOCAVEL&gt;&quot; +   
&quot;    &lt;CONSIGNADO&gt;0&lt;/CONSIGNADO&gt;&quot; +   
&quot;  &lt;/TPrdFil&gt;&quot; +   
&quot;  &lt;TPrdFil&gt;&quot; +   
&quot;    &lt;CODCOLIGADA&gt;1&lt;/CODCOLIGADA&gt;&quot; +   
&quot;    &lt;IDPRD&gt;1&lt;/IDPRD&gt;&quot; +   
&quot;    &lt;CODFILIAL&gt;12&lt;/CODFILIAL&gt;&quot; +   
&quot;    &lt;ESTOCAVEL&gt;1&lt;/ESTOCAVEL&gt;&quot; +   
&quot;    &lt;CONSIGNADO&gt;0&lt;/CONSIGNADO&gt;&quot; +   
&quot;  &lt;/TPrdFil&gt;&quot; +   
&quot;  &lt;TPrdFil&gt;&quot; +   
&quot;    &lt;CODCOLIGADA&gt;1&lt;/CODCOLIGADA&gt;&quot; +   
&quot;    &lt;IDPRD&gt;1&lt;/IDPRD&gt;&quot; +   
&quot;    &lt;CODFILIAL&gt;13&lt;/CODFILIAL&gt;&quot; +   
&quot;    &lt;ESTOCAVEL&gt;1&lt;/ESTOCAVEL&gt;&quot; +   
&quot;    &lt;CONSIGNADO&gt;0&lt;/CONSIGNADO&gt;&quot; +   
&quot;  &lt;/TPrdFil&gt;&quot; +   
&quot;  &lt;TPrdFil&gt;&quot; +   
&quot;    &lt;CODCOLIGADA&gt;1&lt;/CODCOLIGADA&gt;&quot; +   
&quot;    &lt;IDPRD&gt;1&lt;/IDPRD&gt;&quot; +   
&quot;    &lt;CODFILIAL&gt;14&lt;/CODFILIAL&gt;&quot; +   
&quot;    &lt;ESTOCAVEL&gt;1&lt;/ESTOCAVEL&gt;&quot; +   
&quot;    &lt;CONSIGNADO&gt;0&lt;/CONSIGNADO&gt;&quot; +   
&quot;  &lt;/TPrdFil&gt;&quot; +   
&quot;  &lt;TPrdFil&gt;&quot; +   
&quot;    &lt;CODCOLIGADA&gt;1&lt;/CODCOLIGADA&gt;&quot; +   
&quot;    &lt;IDPRD&gt;1&lt;/IDPRD&gt;&quot; +   
&quot;    &lt;CODFILIAL&gt;15&lt;/CODFILIAL&gt;&quot; +   
&quot;    &lt;ESTOCAVEL&gt;1&lt;/ESTOCAVEL&gt;&quot; +   
&quot;    &lt;CONSIGNADO&gt;0&lt;/CONSIGNADO&gt;&quot; +   
&quot;  &lt;/TPrdFil&gt;&quot; +   
&quot;  &lt;TPrdFil&gt;&quot; +   
&quot;    &lt;CODCOLIGADA&gt;1&lt;/CODCOLIGADA&gt;&quot; +   
&quot;    &lt;IDPRD&gt;1&lt;/IDPRD&gt;&quot; +   
&quot;    &lt;CODFILIAL&gt;16&lt;/CODFILIAL&gt;&quot; +   
&quot;    &lt;ESTOCAVEL&gt;1&lt;/ESTOCAVEL&gt;&quot; +   
&quot;    &lt;CONSIGNADO&gt;0&lt;/CONSIGNADO&gt;&quot; +   
&quot;  &lt;/TPrdFil&gt;&quot; +   
&quot;  &lt;TPrdFil&gt;&quot; +   
&quot;    &lt;CODCOLIGADA&gt;1&lt;/CODCOLIGADA&gt;&quot; +   
&quot;    &lt;IDPRD&gt;1&lt;/IDPRD&gt;&quot; +   
&quot;    &lt;CODFILIAL&gt;17&lt;/CODFILIAL&gt;&quot; +   
&quot;    &lt;ESTOCAVEL&gt;1&lt;/ESTOCAVEL&gt;&quot; +   
&quot;    &lt;CONSIGNADO&gt;0&lt;/CONSIGNADO&gt;&quot; +   
&quot;  &lt;/TPrdFil&gt;&quot; +   
&quot;  &lt;TPrdFil&gt;&quot; +   
&quot;    &lt;CODCOLIGADA&gt;1&lt;/CODCOLIGADA&gt;&quot; +   
&quot;    &lt;IDPRD&gt;1&lt;/IDPRD&gt;&quot; +   
&quot;    &lt;CODFILIAL&gt;18&lt;/CODFILIAL&gt;&quot; +   
&quot;    &lt;ESTOCAVEL&gt;1&lt;/ESTOCAVEL&gt;&quot; +   
&quot;    &lt;CONSIGNADO&gt;0&lt;/CONSIGNADO&gt;&quot; +   
&quot;  &lt;/TPrdFil&gt;&quot; +   
&quot;  &lt;TPrdFil&gt;&quot; +   
&quot;    &lt;CODCOLIGADA&gt;1&lt;/CODCOLIGADA&gt;&quot; +   
&quot;    &lt;IDPRD&gt;1&lt;/IDPRD&gt;&quot; +   
&quot;    &lt;CODFILIAL&gt;20&lt;/CODFILIAL&gt;&quot; +   
&quot;    &lt;ESTOCAVEL&gt;1&lt;/ESTOCAVEL&gt;&quot; +   
&quot;    &lt;CONSIGNADO&gt;0&lt;/CONSIGNADO&gt;&quot; +   
&quot;  &lt;/TPrdFil&gt;&quot; +   
&quot;  &lt;TPrdFil&gt;&quot; +   
&quot;    &lt;CODCOLIGADA&gt;1&lt;/CODCOLIGADA&gt;&quot; +   
&quot;    &lt;IDPRD&gt;1&lt;/IDPRD&gt;&quot; +   
&quot;    &lt;CODFILIAL&gt;22&lt;/CODFILIAL&gt;&quot; +   
&quot;    &lt;ESTOCAVEL&gt;1&lt;/ESTOCAVEL&gt;&quot; +   
&quot;    &lt;CONSIGNADO&gt;0&lt;/CONSIGNADO&gt;&quot; +   
&quot;  &lt;/TPrdFil&gt;&quot; +   
&quot;  &lt;TPrdFil&gt;&quot; +   
&quot;    &lt;CODCOLIGADA&gt;1&lt;/CODCOLIGADA&gt;&quot; +   
&quot;    &lt;IDPRD&gt;1&lt;/IDPRD&gt;&quot; +   
&quot;    &lt;CODFILIAL&gt;23&lt;/CODFILIAL&gt;&quot; +   
&quot;    &lt;ESTOCAVEL&gt;1&lt;/ESTOCAVEL&gt;&quot; +   
&quot;    &lt;CONSIGNADO&gt;0&lt;/CONSIGNADO&gt;&quot; +   
&quot;  &lt;/TPrdFil&gt;&quot; +   
&quot;  &lt;TPrdFil&gt;&quot; +   
&quot;    &lt;CODCOLIGADA&gt;1&lt;/CODCOLIGADA&gt;&quot; +   
&quot;    &lt;IDPRD&gt;1&lt;/IDPRD&gt;&quot; +   
&quot;    &lt;CODFILIAL&gt;24&lt;/CODFILIAL&gt;&quot; +   
&quot;    &lt;ESTOCAVEL&gt;1&lt;/ESTOCAVEL&gt;&quot; +   
&quot;    &lt;CONSIGNADO&gt;0&lt;/CONSIGNADO&gt;&quot; +   
&quot;  &lt;/TPrdFil&gt;&quot; +   
&quot;  &lt;TPrdFil&gt;&quot; +   
&quot;    &lt;CODCOLIGADA&gt;1&lt;/CODCOLIGADA&gt;&quot; +   
&quot;    &lt;IDPRD&gt;1&lt;/IDPRD&gt;&quot; +   
&quot;    &lt;CODFILIAL&gt;25&lt;/CODFILIAL&gt;&quot; +   
&quot;    &lt;ESTOCAVEL&gt;1&lt;/ESTOCAVEL&gt;&quot; +   
&quot;    &lt;CONSIGNADO&gt;0&lt;/CONSIGNADO&gt;&quot; +   
&quot;  &lt;/TPrdFil&gt;&quot; +   
&quot;  &lt;TPrdFil&gt;&quot; +   
&quot;    &lt;CODCOLIGADA&gt;1&lt;/CODCOLIGADA&gt;&quot; +   
&quot;    &lt;IDPRD&gt;1&lt;/IDPRD&gt;&quot; +   
&quot;    &lt;CODFILIAL&gt;26&lt;/CODFILIAL&gt;&quot; +   
&quot;    &lt;ESTOCAVEL&gt;1&lt;/ESTOCAVEL&gt;&quot; +   
&quot;    &lt;CONSIGNADO&gt;0&lt;/CONSIGNADO&gt;&quot; +   
&quot;  &lt;/TPrdFil&gt;&quot; +   
&quot;  &lt;TPrdCompl&gt;&quot; +   
&quot;    &lt;CODCOLIGADA&gt;1&lt;/CODCOLIGADA&gt;&quot; +   
&quot;    &lt;IDPRD&gt;1&lt;/IDPRD&gt;&quot; +   
&quot;  &lt;/TPrdCompl&gt;&quot; +   
&quot;&lt;/EstPrdBR&gt;&quot;;
}</eventDescription>
    </WorkflowProcessEvent>
  </list>
  <list/>
  <list>
    <SwimLane>
      <color>C0C0C0</color>
      <height>481</height>
      <width>791</width>
      <positionX>10</positionX>
      <positionY>10</positionY>
      <stateName>Cadastro Produto Estoque</stateName>
      <type>1</type>
      <parentSequence>0</parentSequence>
      <swimLanePK>
        <companyId>1</companyId>
        <processId>rm_cadastro_produto_estoque</processId>
        <version>1</version>
        <sequence>1</sequence>
      </swimLanePK>
    </SwimLane>
    <SwimLane>
      <color>FFFFFF</color>
      <height>160</height>
      <width>761</width>
      <positionX>40</positionX>
      <positionY>10</positionY>
      <stateName>Solicitante</stateName>
      <type>2</type>
      <parentSequence>1</parentSequence>
      <swimLanePK>
        <companyId>1</companyId>
        <processId>rm_cadastro_produto_estoque</processId>
        <version>1</version>
        <sequence>2</sequence>
      </swimLanePK>
    </SwimLane>
    <SwimLane>
      <color>FFFFFF</color>
      <height>160</height>
      <width>761</width>
      <positionX>40</positionX>
      <positionY>170</positionY>
      <stateName>Aprovação</stateName>
      <type>2</type>
      <parentSequence>1</parentSequence>
      <swimLanePK>
        <companyId>1</companyId>
        <processId>rm_cadastro_produto_estoque</processId>
        <version>1</version>
        <sequence>3</sequence>
      </swimLanePK>
    </SwimLane>
    <SwimLane>
      <color>FFFFFF</color>
      <height>161</height>
      <width>761</width>
      <positionX>40</positionX>
      <positionY>330</positionY>
      <stateName>TOTVS RM</stateName>
      <type>2</type>
      <parentSequence>1</parentSequence>
      <swimLanePK>
        <companyId>1</companyId>
        <processId>rm_cadastro_produto_estoque</processId>
        <version>1</version>
        <sequence>4</sequence>
      </swimLanePK>
    </SwimLane>
  </list>
  <list>
    <ProcessComponGraf>
      <componType>1</componType>
      <positionX>620</positionX>
      <positionY>208</positionY>
      <processComponGrafPK>
        <companyId>1</companyId>
        <processId>rm_cadastro_produto_estoque</processId>
        <version>1</version>
        <componGrafSequence>16</componGrafSequence>
      </processComponGrafPK>
      <stateName>Reprovado Gestor</stateName>
    </ProcessComponGraf>
    <ProcessComponGraf>
      <componType>1</componType>
      <positionX>630</positionX>
      <positionY>392</positionY>
      <processComponGrafPK>
        <companyId>1</companyId>
        <processId>rm_cadastro_produto_estoque</processId>
        <version>1</version>
        <componGrafSequence>17</componGrafSequence>
      </processComponGrafPK>
      <stateName>Cadastro Produto no TOTVS RM</stateName>
    </ProcessComponGraf>
  </list>
  <list>
    <ProcessLinkAssoc>
      <processLinkAssocPK>
        <companyId>1</companyId>
        <processId>rm_cadastro_produto_estoque</processId>
        <version>1</version>
        <linkSequence>19</linkSequence>
      </processLinkAssocPK>
      <initialStateSequence>16</initialStateSequence>
      <finalStateSequence>13</finalStateSequence>
    </ProcessLinkAssoc>
    <ProcessLinkAssoc>
      <processLinkAssocPK>
        <companyId>1</companyId>
        <processId>rm_cadastro_produto_estoque</processId>
        <version>1</version>
        <linkSequence>26</linkSequence>
      </processLinkAssocPK>
      <initialStateSequence>17</initialStateSequence>
      <finalStateSequence>24</finalStateSequence>
    </ProcessLinkAssoc>
  </list>
  <list>
    <ProcessLinkBend>
      <processLinkBendPK>
        <companyId>1</companyId>
        <processId>rm_cadastro_produto_estoque</processId>
        <version>9</version>
        <linkSequence>27</linkSequence>
        <bendSequence>1</bendSequence>
      </processLinkBendPK>
      <positionX>167</positionX>
      <positionY>235</positionY>
    </ProcessLinkBend>
  </list>
  <list/>
  <list/>
  <list/>
  <list>
    <ProcessStateService>
      <companyId>1</companyId>
      <processId>rm_cadastro_produto_estoque</processId>
      <version>1</version>
      <sequence>20</sequence>
      <attempts>0</attempts>
      <sucessFullMessage>Integração executada com sucesso</sucessFullMessage>
      <serviceName></serviceName>
      <frequency>1</frequency>
      <frequencyType>0</frequencyType>
    </ProcessStateService>
  </list>
  <list/>
  <list/>
  <list/>
  <list/>
</list>